kompot/__init__.py
kompot/batch_utils.py
kompot/memory_utils.py
kompot/resource_estimation.py
kompot/utils.py
kompot/version.py
kompot/anndata/__init__.py
kompot/anndata/cleanup.py
kompot/anndata/differential_abundance.py
kompot/anndata/differential_expression.py
kompot/anndata/fdr_utils.py
kompot/anndata/utils.py
kompot/anndata/utils/__init__.py
kompot/anndata/utils/field_tracking.py
kompot/anndata/utils/group_utils.py
kompot/anndata/utils/json_utils.py
kompot/anndata/utils/runinfo.py
kompot/differential/__init__.py
kompot/differential/differential_abundance.py
kompot/differential/differential_expression.py
kompot/differential/sample_variance_estimator.py
kompot/differential/utils.py
kompot/plot/__init__.py
kompot/plot/embedding.py
kompot/plot/expression.py
kompot/plot/field_inference.py
kompot/plot/heatmap.py
kompot/plot/stringdb.py
kompot/plot/volcano.py
kompot/plot/heatmap/__init__.py
kompot/plot/heatmap/core.py
kompot/plot/heatmap/direction_plot.py
kompot/plot/heatmap/utils.py
kompot/plot/heatmap/visualization.py
kompot/plot/volcano/__init__.py
kompot/plot/volcano/da.py
kompot/plot/volcano/de.py
kompot/plot/volcano/multi_da.py
kompot/plot/volcano/utils.py
kompot-0.5.2.dist-info/licenses/LICENSE
kompot-0.5.2.dist-info/METADATA
kompot-0.5.2.dist-info/WHEEL
kompot-0.5.2.dist-info/top_level.txt
kompot-0.5.2.dist-info/RECORD
