Metadata-Version: 2.4
Name: kompot
Version: 0.5.2
Summary: Differential abundance and gene expression analysis using Mahalanobis distance with JAX backend
Author-email: Dominik Otto <dotto@fredhutch.org>
License-Expression: GPL-3.0-or-later
Project-URL: Homepage, https://github.com/settylab/kompot
Project-URL: Documentation, https://kompot.readthedocs.io/
Project-URL: Bug Tracker, https://github.com/settylab/kompot/issues
Classifier: Development Status :: 4 - Beta
Classifier: Intended Audience :: Science/Research
Classifier: Programming Language :: Python :: 3
Classifier: Programming Language :: Python :: 3.9
Classifier: Programming Language :: Python :: 3.10
Classifier: Programming Language :: Python :: 3.11
Classifier: Programming Language :: Python :: 3.13
Classifier: Topic :: Scientific/Engineering :: Bio-Informatics
Requires-Python: >=3.9
License-File: LICENSE
Requires-Dist: numpy>=1.20.0
Requires-Dist: scipy>=1.7.0
Requires-Dist: pandas>=1.3.0
Requires-Dist: scikit-learn>=1.0.0
Requires-Dist: statsmodels>=0.13.0
Requires-Dist: jax>=0.3.0
Requires-Dist: jaxlib>=0.3.0
Requires-Dist: mellon>=1.6.0
Requires-Dist: matplotlib>=3.5.0
Requires-Dist: tqdm>=4.60.0
Requires-Dist: anndata>=0.8.0
Requires-Dist: pynndescent>=0.5.0
Requires-Dist: python-igraph>=0.10.0
Requires-Dist: psutil>=5.9.0
Requires-Dist: filelock>=3.12.0
Requires-Dist: importlib-resources>=5.0.0; python_version < "3.9"
Provides-Extra: docs
Requires-Dist: sphinx<8.3.0,>=7.0.0; extra == "docs"
Requires-Dist: nbsphinx>=0.9.0; extra == "docs"
Requires-Dist: furo>=2024.0.0; extra == "docs"
Requires-Dist: sphinx-github-style>=1.2.0; extra == "docs"
Requires-Dist: lxml[html_clean]; extra == "docs"
Requires-Dist: IPython; extra == "docs"
Provides-Extra: plot
Requires-Dist: scanpy>=1.9.0; extra == "plot"
Requires-Dist: matplotlib>=3.5.0; extra == "plot"
Requires-Dist: requests>=2.28.0; extra == "plot"
Requires-Dist: IPython>=7.0.0; extra == "plot"
Requires-Dist: json5~=0.9.14; extra == "plot"
Provides-Extra: recommended
Requires-Dist: palantir>=1.0.0; extra == "recommended"
Requires-Dist: dask>=2024.4.0; extra == "recommended"
Provides-Extra: dask
Requires-Dist: dask>=2024.4.0; extra == "dask"
Provides-Extra: dev
Requires-Dist: pytest>=7.0.0; extra == "dev"
Requires-Dist: pytest-cov>=4.0.0; extra == "dev"
Provides-Extra: all
Requires-Dist: scanpy>=1.9.0; extra == "all"
Requires-Dist: matplotlib>=3.5.0; extra == "all"
Requires-Dist: requests>=2.28.0; extra == "all"
Requires-Dist: IPython>=7.0.0; extra == "all"
Requires-Dist: json5~=0.9.14; extra == "all"
Requires-Dist: palantir>=1.0.0; extra == "all"
Requires-Dist: dask>=2024.4.0; extra == "all"
Dynamic: license-file
